b3p/__init__.py
b3p/anba/__init__.py
b3p/anba/anba4_prep.py
b3p/anba/anba4_solve.py
b3p/anba/mesh_2d.py
b3p/bem/__init__.py
b3p/bem/ccblade_run.py
b3p/ccx/__init__.py
b3p/ccx/ccx2vtu.py
b3p/ccx/ccxpost.py
b3p/ccx/failcrit_mesh.py
b3p/ccx/mesh2ccx.py
b3p/ccx/plot_ccx.py
b3p/cli/__init__.py
b3p/cli/app_state.py
b3p/cli/build_app.py
b3p/cli/ccblade_app.py
b3p/cli/ccx_app.py
b3p/cli/clean_app.py
b3p/cli/main.py
b3p/cli/two_d_app.py
b3p/cli/utils.py
b3p/cli/validate_app.py
b3p/cli/yml_portable.py
b3p/geometry/__init__.py
b3p/geometry/blade.py
b3p/geometry/blade_section.py
b3p/geometry/build_blade_geometry.py
b3p/geometry/geom_utils.py
b3p/geometry/geometry_blade_shape.py
b3p/geometry/geometry_section.py
b3p/geometry/geometry_web.py
b3p/geometry/loft_utils.py
b3p/geometry/splining.py
b3p/laminates/__init__.py
b3p/laminates/build_plybook.py
b3p/laminates/drape_mesh.py
b3p/laminates/drape_summary.py
b3p/mesh/add_load_to_mesh.py
b3p/mesh/add_te_solids.py
b3p/mesh/build_blade_structure.py
b3p/mesh/combine_meshes.py
b3p/mesh/mesh_from_loft.py
b3p/mesh/webs.py
b3p/models/__init__.py
b3p/models/config.py
b3p/models/defaults.yaml
b3p/models/materials.py
b3p-0.1.9.dist-info/METADATA
b3p-0.1.9.dist-info/WHEEL
b3p-0.1.9.dist-info/entry_points.txt
b3p-0.1.9.dist-info/licenses/LICENSE.md
b3p-0.1.9.dist-info/RECORD
