Metadata-Version: 2.4
Name: b3p
Version: 0.1.9
Summary: Command line tools for preprocessing of wind turbine blade models
Author-email: wr1 <8971152+wr1@users.noreply.github.com>
License: MIT
License-File: LICENSE.md
Requires-Python: <4.0.0,>=3.11
Requires-Dist: frd2vtu>=0.1.6
Requires-Dist: h5py<4.0.0,>=3.11.0
Requires-Dist: jinja2<4.0.0,>=3.1.4
Requires-Dist: meshio<6.0.0,>=5.3.5
Requires-Dist: mkdocs-material<10.0.0,>=9.6.1
Requires-Dist: numpy>=2.3.1
Requires-Dist: pandas<3.0.0,>=2.2.3
Requires-Dist: pyarrow>18
Requires-Dist: pydantic>=2.11.7
Requires-Dist: pytest<9.0.0,>=8.3.3
Requires-Dist: pyvista>=0.44.2
Requires-Dist: ruamel-yaml==0.18.11
Requires-Dist: scipy<2.0.0,>=1.13.0
Requires-Dist: sympy<2.0.0,>=1.13.3
Requires-Dist: tqdm<5.0.0,>=4.66.5
Requires-Dist: vtk==9.3.1
